gcp_route_optimizer/__init__.py
gcp_route_optimizer/builders.py
gcp_route_optimizer/google_api.py
gcp_route_optimizer/google_token.py
gcp_route_optimizer/optimizer.py
gcp_route_optimizer-1.0.1.dist-info/licenses/LICENSE
gcp_route_optimizer-1.0.1.dist-info/METADATA
gcp_route_optimizer-1.0.1.dist-info/WHEEL
gcp_route_optimizer-1.0.1.dist-info/top_level.txt
gcp_route_optimizer-1.0.1.dist-info/RECORD
