Metadata-Version: 2.4
Name: gcp-route-optimizer
Version: 1.0.1
Summary: A lightweight wrapper for Google Fleet Routing / OptimizeTours API.
Author: Preethi Gopinath
License: MIT License
Keywords: google,routing,fleet,optimizer,maps,logistics
Classifier: Programming Language :: Python :: 3
Classifier: License :: OSI Approved :: MIT License
Classifier: Operating System :: OS Independent
Requires-Python: >=3.9
License-File: LICENSE
Requires-Dist: requests
Requires-Dist: google-auth
Dynamic: license-file
